test_pb2.py
test_pb2_grpc.py
hamzamania-0.1.dist-info/METADATA
hamzamania-0.1.dist-info/WHEEL
hamzamania-0.1.dist-info/top_level.txt
hamzamania-0.1.dist-info/RECORD
