Metadata-Version: 2.1
Name: hamzamania
Version: 0.1
Summary: This is for you Ali g, Staines massive big upp
Home-page: UNKNOWN
Author: Amir Kidwai
Author-email: findamirkidwai@gmail.com
License: UNKNOWN
Platform: UNKNOWN
Classifier: Programming Language :: Python :: 3
Classifier: License :: OSI Approved :: MIT License
Classifier: Operating System :: OS Independent
Requires-Python: >=3.6
